<?xml version="1.0" encoding="utf-8" ?>
<c2eventsheet>
    <!--All the 'name' attributes are ignored by Construct 2 - they are there for readability only.-->
    <name>Title</name>
    <events>
        <event-block sid="6871710781650088">
            <conditions>
                <condition id="-2" name="On start of layout" sid="6307488861812338" type="System" />
            </conditions>
            <actions>
                <action id="5" name="Set web font" sid="9115375363570796" type="Title">
                    <param id="0" name="Family name">&quot;molotregular&quot;</param>
                    <param id="1" name="CSS URL">&quot;stylesheet.css&quot;</param>
                </action>
                <action id="-16" name="Wait" sid="3264520496998294" type="System">
                    <param id="0" name="Seconds">0.1</param>
                </action>
                <action id="-25" name="Move to bottom" sid="6271378975027621" type="Background" />
            </actions>
        </event-block>
        <event-block sid="5146629636009266">
            <conditions>
                <condition id="1" name="On any click" sid="6218808921545933" type="Mouse" />
            </conditions>
            <actions>
                <action id="-2" name="Go to layout" sid="7233226532793044" type="System">
                    <param id="0" name="Layout">Board</param>
                </action>
            </actions>
        </event-block>
        <event-block sid="4442900825701292">
            <conditions>
                <condition id="14" name="On tap" sid="3107992936835374" type="Touch" />
            </conditions>
            <actions>
                <action id="-2" name="Go to layout" sid="2289492307894343" type="System">
                    <param id="0" name="Layout">Board</param>
                </action>
            </actions>
        </event-block>
    </events>
</c2eventsheet>
